mtc/__init__.py
mtc/touch.py
mtc_base-0.0.3.dist-info/METADATA
mtc_base-0.0.3.dist-info/WHEEL
mtc_base-0.0.3.dist-info/top_level.txt
mtc_base-0.0.3.dist-info/RECORD
